examplepy/__init__.py
examplepy/cashpiggy.py
cashpiggy_am-0.1.0.dist-info/LICENSE
cashpiggy_am-0.1.0.dist-info/METADATA
cashpiggy_am-0.1.0.dist-info/WHEEL
cashpiggy_am-0.1.0.dist-info/top_level.txt
cashpiggy_am-0.1.0.dist-info/RECORD
