Metadata-Version: 2.1
Name: cashpiggy-am
Version: 0.1.0
Summary: An API wrapper around the caspiggy mobile app.
Home-page: https://github.com/AdonisCodes/CashPiggy-am
Author: AdonisCodes
Author-email: business@simonferns.com
Project-URL: Documentation, https://github.com/AdonisCodes/CashPiggy-am
Project-URL: Bug Reports, https://github.com/AdonisCodes/CashPiggy-am/issues
Project-URL: Source Code, https://github.com/AdonisCodes/CashPiggy-am
Keywords: package,automation,cashpiggy,mobile-app
Classifier: Development Status :: 5 - Production/Stable
Classifier: Intended Audience :: Developers
Classifier: Topic :: Software Development :: Build Tools
Classifier: Programming Language :: Python :: 3
Classifier: Programming Language :: Python :: 3.6
Classifier: Programming Language :: Python :: 3.7
Classifier: Programming Language :: Python :: 3.8
Classifier: Programming Language :: Python :: 3.9
Classifier: Programming Language :: Python :: 3 :: Only
Classifier: License :: OSI Approved :: MIT License
Classifier: Operating System :: OS Independent
Requires-Python: >=3.6
License-File: LICENSE
Requires-Dist: requests
